change_permisions.py
locate_file.py
ls.py
env/Lib/site-packages/oschmod/cli.py
windows_unix_commands-0.0.7.dist-info/METADATA
windows_unix_commands-0.0.7.dist-info/WHEEL
windows_unix_commands-0.0.7.dist-info/entry_points.txt
windows_unix_commands-0.0.7.dist-info/top_level.txt
windows_unix_commands-0.0.7.dist-info/RECORD
