Metadata-Version: 2.1
Name: windows-unix-commands
Version: 0.0.7
Summary: hey
Home-page: UNKNOWN
Author: UNKNOWN
Author-email: UNKNOWN
License: UNKNOWN
Platform: UNKNOWN
Requires-Dist: oschmod
